{"name":"Pets Promotional","left":[{"name":"misc","itemData":[{"id":"34493","name":"Dragon Kite","quality":"4","icon":"inv_misc_dragonkite_02","htmlTooltip":"<table><tr><td><b class=\"q4\">Dragon Kite</b><br /><!--bo-->Binds when picked up<br /><!--e--><!--ps--></td></tr></table><table><tr><td><span class=\"q2\">Use:  <a href=\"?spell=45127\">Teaches you how to summon this companion.</a></span><br /><span class=\"q1\">1 Charge</span><br /></td></tr></table>","link":"https://wotlkdb.com?item=34493","ilvl":"1","wowClass":"15","wowSubClass":"2","slot":"0"},{"id":"23713","name":"Hippogryph Hatchling","quality":"4","icon":"inv_egg_02","htmlTooltip":"<table><tr><td><b class=\"q4\">Hippogryph Hatchling</b><br /><!--bo-->Binds when picked up<br /><!--e--><!--ps--></td></tr></table><table><tr><td><span class=\"q2\">Use:  <a href=\"?spell=30156\">Teaches you how to summon this companion.</a></span><br /><span class=\"q1\">1 Charge</span><br /></td></tr></table>","link":"https://wotlkdb.com?item=23713","ilvl":"1","wowClass":"15","wowSubClass":"2","slot":"0"},{"id":"49287","name":"Tuskarr Kite","quality":"4","icon":"inv_misc_pet_01","htmlTooltip":"<table><tr><td><b class=\"q4\">Tuskarr Kite</b><br /><!--bo-->Binds when picked up<br /><!--e--><!--ps--></td></tr></table><table><tr><td><span class=\"q2\">Use:  <a href=\"?spell=68767\">Teaches you how to summon this companion.</a></span><br /><span class=\"q1\">1 Charge</span><br /></td></tr></table>","link":"https://wotlkdb.com?item=49287","ilvl":"1","wowClass":"15","wowSubClass":"2","slot":"0"},{"id":"32588","name":"Banana Charm","quality":"3","icon":"inv_misc_food_24","htmlTooltip":"<table><tr><td><b class=\"q3\">Banana Charm</b><br /><!--bo-->Binds when picked up<br /><!--e--><!--ps--></td></tr></table><table><tr><td><span class=\"q2\">Use:  <a href=\"?spell=40549\">Teaches you how to summon this companion.</a></span><br /><span class=\"q1\">1 Charge</span><br /></td></tr></table>","link":"https://wotlkdb.com?item=32588","ilvl":"1","wowClass":"15","wowSubClass":"2","slot":"0"},{"id":"20371","name":"Blue Murloc Egg","quality":"3","icon":"inv_egg_03","htmlTooltip":"<table><tr><td><b class=\"q3\">Blue Murloc Egg</b><br /><!--bo-->Binds to account<br />Unique<br /><!--e--><!--ps--></td></tr></table><table><tr><td><span class=\"q2\">Use:  <a href=\"?spell=24696\">Teaches you how to summon this companion.</a></span><br /></td></tr></table>","link":"https://wotlkdb.com?item=20371","ilvl":"20","wowClass":"15","wowSubClass":"2","slot":"0"},{"id":"13584","name":"Diablo Stone","quality":"3","icon":"inv_diablostone","htmlTooltip":"<table><tr><td><b class=\"q3\">Diablo Stone</b><br /><!--bo-->Binds to account<br /><!--e--><!--ps--></td></tr></table><table><tr><td><span class=\"q2\">Use:  <a href=\"?spell=17708\">Teaches you how to summon this companion.</a></span><br /></td></tr></table>","link":"https://wotlkdb.com?item=13584","ilvl":"20","wowClass":"15","wowSubClass":"2","slot":"0"},{"id":"39286","name":"Frosty's Collar","quality":"3","icon":"inv_pet_frostwyrm","htmlTooltip":"<table><tr><td><b class=\"q3\">Frosty's Collar</b><br /><!--bo-->Binds to account<br /><!--e--><!--ps--></td></tr></table><table><tr><td><span class=\"q2\">Use:  <a href=\"?spell=52615\">Teaches you how to summon Frosty!</a></span><br /></td></tr></table>","link":"https://wotlkdb.com?item=39286","ilvl":"20","wowClass":"15","wowSubClass":"2","slot":"0"},{"id":"37297","name":"Gold Medallion","quality":"3","icon":"inv_jewelry_amulet_03","htmlTooltip":"<table><tr><td><b class=\"q3\">Gold Medallion</b><br /><!--bo-->Binds when picked up<br />Unique<br /><!--e--><!--ps--></td></tr></table><table><tr><td><span class=\"q2\">Use:  <a href=\"?spell=48406\">Teaches you how to summon this companion.</a></span><br /><span class=\"q1\">1 Charge</span><br /></td></tr></table>","link":"https://wotlkdb.com?item=37297","ilvl":"1","wowClass":"15","wowSubClass":"2","slot":"0"},{"id":"46802","name":"Heavy Murloc Egg","quality":"3","icon":"inv_egg_03","htmlTooltip":"<table><tr><td><b class=\"q3\">Heavy Murloc Egg</b><br /><!--bo-->Binds when picked up<br />Unique<br /><!--e--><!--ps--></td></tr></table><table><tr><td><span class=\"q2\">Use:  <a href=\"?spell=66030\">Teaches you how to summon this companion.</a></span><br /><span class=\"q1\">1 Charge</span><br /></td></tr></table>","link":"https://wotlkdb.com?item=46802","ilvl":"20","wowClass":"15","wowSubClass":"2","slot":"0"},{"id":"30360","name":"Lurky's Egg","quality":"3","icon":"inv_egg_03","htmlTooltip":"<table><tr><td><b class=\"q3\">Lurky's Egg</b><br /><!--bo-->Binds to account<br /><!--e--><!--ps--></td></tr></table><table><tr><td><span class=\"q2\">Use:  <a href=\"?spell=24988\">Teaches you how to summon this companion.</a></span><br /></td></tr></table>","link":"https://wotlkdb.com?item=30360","ilvl":"1","wowClass":"15","wowSubClass":"2","slot":"0"},{"id":"45180","name":"Murkimus' Little Spear","quality":"3","icon":"inv_spear_05","htmlTooltip":"<table><tr><td><b class=\"q3\">Murkimus' Little Spear</b><br /><!--bo-->Binds when picked up<br />Unique<br /><!--e--><!--ps--></td></tr></table><table><tr><td><span class=\"q2\">Use:  <a href=\"?spell=63318\">Teaches you how to summon this companion.</a></span><br /><span class=\"q1\">1 Charge</span><br /></td></tr></table>","link":"https://wotlkdb.com?item=45180","ilvl":"20","wowClass":"15","wowSubClass":"2","slot":"0"},{"id":"25535","name":"Netherwhelp's Collar","quality":"3","icon":"inv_netherwhelp","htmlTooltip":"<table><tr><td><b class=\"q3\">Netherwhelp's Collar</b><br /><!--bo-->Binds to account<br /><!--e--><!--ps--></td></tr></table><table><tr><td><span class=\"q2\">Use:  <a href=\"?spell=32298\">Teaches you how to summon this companion.</a></span><br /></td></tr></table>","link":"https://wotlkdb.com?item=25535","ilvl":"20","wowClass":"15","wowSubClass":"2","slot":"0"},{"id":"13583","name":"Panda Collar","quality":"3","icon":"inv_belt_05","htmlTooltip":"<table><tr><td><b class=\"q3\">Panda Collar</b><br /><!--bo-->Binds to account<br /><!--e--><!--ps--></td></tr></table><table><tr><td><span class=\"q2\">Use:  <a href=\"?spell=17707\">Teaches you how to summon this companion.</a></span><br /></td></tr></table>","link":"https://wotlkdb.com?item=13583","ilvl":"20","wowClass":"15","wowSubClass":"2","slot":"0"},{"id":"22114","name":"Pink Murloc Egg","quality":"3","icon":"inv_pet_pinkmurlocegg","htmlTooltip":"<table><tr><td><b class=\"q3\">Pink Murloc Egg</b><br /><!--bo-->Binds to account<br />Unique<br /><!--e--><!--ps--></td></tr></table><table><tr><td><span class=\"q2\">Use:  <a href=\"?spell=27241\">Teaches you how to summon this companion.</a></span><br /></td></tr></table>","link":"https://wotlkdb.com?item=22114","ilvl":"20","wowClass":"15","wowSubClass":"2","slot":"0"},{"id":"34492","name":"Rocket Chicken","quality":"3","icon":"inv_misc_enggizmos_rocketchicken","htmlTooltip":"<table><tr><td><b class=\"q3\">Rocket Chicken</b><br /><!--bo-->Binds when picked up<br /><!--e--><!--ps--></td></tr></table><table><tr><td><span class=\"q2\">Use:  <a href=\"?spell=45125\">Teaches you how to summon this companion.</a></span><br /><span class=\"q1\">1 Charge</span><br /></td></tr></table>","link":"https://wotlkdb.com?item=34492","ilvl":"1","wowClass":"15","wowSubClass":"2","slot":"0"},{"id":"38050","name":"Soul-Trader Beacon","quality":"3","icon":"spell_nature_groundingtotem","htmlTooltip":"<table><tr><td><b class=\"q3\">Soul-Trader Beacon</b><br /><!--bo-->Binds when picked up<br /><!--e--><!--ps--></td></tr></table><table><tr><td><span class=\"q2\">Use:  <a href=\"?spell=49964\">Teaches you how to summon this companion.</a></span><br /><span class=\"q1\">1 Charge</span><br /></td></tr></table>","link":"https://wotlkdb.com?item=38050","ilvl":"20","wowClass":"15","wowSubClass":"2","slot":"0"},{"id":"49343","name":"Spectral Tiger Cub","quality":"3","icon":"ability_mount_spectraltiger","htmlTooltip":"<table><tr><td><b class=\"q3\">Spectral Tiger Cub</b><br /><!--bo-->Binds when picked up<br /><!--e--><!--ps--></td></tr></table><table><tr><td><span class=\"q2\">Use:  <a href=\"?spell=68810\">Teaches you how to summon this companion.</a></span><br /><span class=\"q1\">1 Charge</span><br /></td></tr></table>","link":"https://wotlkdb.com?item=49343","ilvl":"1","wowClass":"15","wowSubClass":"2","slot":"0"},{"id":"39656","name":"Tyrael's Hilt","quality":"3","icon":"inv_sword_07","htmlTooltip":"<table><tr><td><b class=\"q3\">Tyrael's Hilt</b><br /><!--bo-->Binds to account<br /><!--e--><!--ps--></td></tr></table><table><tr><td><span class=\"q2\">Use:  <a href=\"?spell=53082\">Teaches you how to summon this companion.</a></span><br /></td></tr></table>","link":"https://wotlkdb.com?item=39656","ilvl":"20","wowClass":"15","wowSubClass":"2","slot":"0"},{"id":"41133","name":"Unhatched Mr. Chilly","quality":"3","icon":"inv_misc_penguinpet","htmlTooltip":"<table><tr><td><b class=\"q3\">Unhatched Mr. Chilly</b><br /><!--bo-->Binds when picked up<br /><!--e--><!--ps--></td></tr></table><table><tr><td><span class=\"q2\">Use:  <a href=\"?spell=55068\">Teaches you how to summon Mr. Chilly.</a></span><br /><span class=\"q1\">1 Charge</span><br /></td></tr></table>","link":"https://wotlkdb.com?item=41133","ilvl":"20","wowClass":"15","wowSubClass":"2","slot":"0"},{"id":"46767","name":"Warbot Ignition Key","quality":"3","icon":"inv_misc_key_05","htmlTooltip":"<table><tr><td><b class=\"q3\">Warbot Ignition Key</b><br /><!--bo-->Binds when picked up<br />Unique<br /><!--e--><!--ps--></td></tr></table><table><tr><td><span class=\"q2\">Use:  <a href=\"?spell=65682\">Teaches you how to summon this companion.</a></span><br /><span class=\"q1\">1 Charge</span><br /></td></tr></table>","link":"https://wotlkdb.com?item=46767","ilvl":"20","wowClass":"15","wowSubClass":"2","slot":"0"},{"id":"13582","name":"Zergling Leash","quality":"3","icon":"spell_shadow_summonfelhunter","htmlTooltip":"<table><tr><td><b class=\"q3\">Zergling Leash</b><br /><!--bo-->Binds to account<br /><!--e--><!--ps--></td></tr></table><table><tr><td><span class=\"q2\">Use:  <a href=\"?spell=17709\">Teaches you how to summon this companion.</a></span><br /></td></tr></table>","link":"https://wotlkdb.com?item=13582","ilvl":"20","wowClass":"15","wowSubClass":"2","slot":"0"},{"id":"56806","name":"Mini Thor","quality":"3","icon":"t_roboticon","htmlTooltip":"<table><tr><td><b class=\"q3\">Mini Thor</b><br /><!--bo-->Binds to account<br /><!--e--><!--ps--></td></tr></table><table><tr><td><span class=\"q2\">Use:  <a href=\"?spell=78381\">Teaches you how to summon Mini Thor.</a></span><br /></td></tr></table>","link":"https://wotlkdb.com?item=56806","ilvl":"20","wowClass":"15","wowSubClass":"2","slot":"0"}]}],"mid":[],"right":[]}