{"id":-20034,"name":"Enchant Weapon - Crusader","icon":"spell_holy_greaterheal","htmlTooltip":"<table><tr><td><b>Enchant Weapon - Crusader</b></td></tr></table><table><tr><td><span class=\"q\">Permanently enchant a melee weapon to often heal for 75 to 125 and increase Strength by 100 for 15 sec. when attacking in melee. Has a reduced effect for players above level 60.</span></td></tr></table>","quality":1,"link":"https://wotlkdb.com/?spell=20034","ilvl":0,"wowClass":-69,"wowSubClass":0,"slot":0,"createdBy":[{"id":0,"name":"Enchant Weapon - Crusader","icon":"","reagents":[{"id":14344,"name":"Large Brilliant Shard","icon":"inv_enchant_shardbrilliantlarge","count":4,"quality":"3"},{"id":12811,"name":"Righteous Orb","icon":"inv_misc_gem_pearl_03","count":2,"quality":"2"}]}]}