{"name":"Freya","descr":"descr","loot":[45038,46017,45483,45482,45481,45480,45479,45653,45654,45655,46110,45486,45488,45487,45485,45484,45613,45814],"lootHeroic":[],"sortedLoot":{"armor":["45486","45483","45488","45482","45481","45487"],"jewelry":["45480","45485"],"weapons":["46017","45479","45613","45484"],"misc":["45038","46110","45814"],"tokens":["45653","45654","45655"]},"sortedLootItems":{"armor":[{"id":"45486","name":"Drape of the Sullen Goddess","quality":"4","icon":"inv_misc_cape_naxxramas_02","htmlTooltip":"<table><tr><td><b class=\"q4\">Drape of the Sullen Goddess</b><br /><!--bo-->Binds when picked up<table width=\"100%\"><tr><td>Back</td></tr></table><span><!--amr-->162 Armor</span><br /><span><!--stat7-->+61 Stamina</span><br /><span><!--stat5-->+51 Intellect</span><br /><!--e--><span class=\"socket-yellow q0\" >Yellow Socket</span><br /><!--ps--><span class=\"q0\">Socket Bonus: <a href=\"?enchantment=3752\">+5 Spell Power</a></span><br />Requires Level 80<br />Item Level 239<br /></td></tr></table><table><tr><td><span class=\"q2\">Equip: Increases spell power by <!--rtg45-->75.</span><br /><span class=\"q2\">Equip: Improves critical strike rating by <!--rtg32-->40&nbsp;<small>(<!--rtg%32-->0.87%&nbsp;@&nbsp;L<!--lvl-->80)</small>.</span><br /><span class=\"q2\">Equip: Restores <!--rtg43-->24 mana per 5 sec.</span><br /><div class=\"q1 whtt-sellprice\">Sell Price: <span class=\"moneygold\">6</span> <span class=\"moneysilver\">94</span> <span class=\"moneycopper\">75</span></div></td></tr></table><!--?45486:1:80:80-->","link":"https://wotlkdb.com?item=45486","ilvl":"239","wowClass":"4","wowSubClass":"-6","slot":"16"},{"id":"45483","name":"Boots of the Servant","quality":"4","icon":"inv_boots_cloth_03","htmlTooltip":"<table><tr><td><b class=\"q4\">Boots of the Servant</b><br /><!--bo-->Binds when picked up<table width=\"100%\"><tr><td>Feet</td><th><!--asc1-->Cloth</th></tr></table><span><!--amr-->216 Armor</span><br /><span><!--stat7-->+73 Stamina</span><br /><span><!--stat5-->+56 Intellect</span><br /><span><!--stat6-->+48 Spirit</span><br /><!--e--><span class=\"socket-blue q0\" >Blue Socket</span><br /><!--ps--><span class=\"q0\">Socket Bonus: <a href=\"?enchantment=3752\">+5 Spell Power</a></span><br />Durability 50 / 50<br />Requires Level 80<br />Item Level 226<br /></td></tr></table><table><tr><td><span class=\"q2\">Equip: Increases spell power by <!--rtg45-->90.</span><br /><span class=\"q2\">Equip: Increases your haste rating by <!--rtg36-->62&nbsp;<small>(<!--rtg%36-->1.89%&nbsp;@&nbsp;L<!--lvl-->80)</small>.</span><br /><div class=\"q1 whtt-sellprice\">Sell Price: <span class=\"moneygold\">6</span> <span class=\"moneysilver\">33</span> <span class=\"moneycopper\">93</span></div></td></tr></table><!--?45483:1:80:80-->","link":"https://wotlkdb.com?item=45483","ilvl":"226","wowClass":"4","wowSubClass":"1","slot":"8"},{"id":"45488","name":"Leggings of the Enslaved Idol","quality":"4","icon":"inv_pants_cloth_27","htmlTooltip":"<table><tr><td><b class=\"q4\">Leggings of the Enslaved Idol</b><br /><!--bo-->Binds when picked up<table width=\"100%\"><tr><td>Legs</td><th><!--asc1-->Cloth</th></tr></table><span><!--amr-->284 Armor</span><br /><span><!--stat7-->+96 Stamina</span><br /><span><!--stat5-->+98 Intellect</span><br /><!--e--><span class=\"socket-red q0\" >Red Socket</span><br /><span class=\"socket-yellow q0\" >Yellow Socket</span><br /><span class=\"socket-blue q0\" >Blue Socket</span><br /><!--ps--><span class=\"q0\">Socket Bonus: <a href=\"?enchantment=3753\">+9 Spell Power</a></span><br />Durability 75 / 75<br />Requires Level 80<br />Item Level 239<br /></td></tr></table><table><tr><td><span class=\"q2\">Equip: Increases spell power by <!--rtg45-->122.</span><br /><span class=\"q2\">Equip: Improves hit rating by <!--rtg31-->70&nbsp;<small>(<!--rtg%31-->2.13%&nbsp;@&nbsp;L<!--lvl-->80)</small>.</span><br /><span class=\"q2\">Equip: Improves critical strike rating by <!--rtg32-->77&nbsp;<small>(<!--rtg%32-->1.68%&nbsp;@&nbsp;L<!--lvl-->80)</small>.</span><br /><div class=\"q1 whtt-sellprice\">Sell Price: <span class=\"moneygold\">9</span> <span class=\"moneysilver\">33</span> <span class=\"moneycopper\">12</span></div></td></tr></table><!--?45488:1:80:80-->","link":"https://wotlkdb.com?item=45488","ilvl":"239","wowClass":"4","wowSubClass":"1","slot":"7"},{"id":"45482","name":"Leggings of the Lifetender","quality":"4","icon":"inv_pants_leather_28","htmlTooltip":"<table><tr><td><b class=\"q4\">Leggings of the Lifetender</b><br /><!--bo-->Binds when picked up<table width=\"100%\"><tr><td>Legs</td><th><!--asc2-->Leather</th></tr></table><span><!--amr-->517 Armor</span><br /><span><!--stat7-->+99 Stamina</span><br /><span><!--stat5-->+81 Intellect</span><br /><span><!--stat6-->+76 Spirit</span><br /><!--e--><span class=\"socket-red q0\" >Red Socket</span><br /><span class=\"socket-blue q0\" >Blue Socket</span><br /><!--ps--><span class=\"q0\">Socket Bonus: <a href=\"?enchantment=3311\">+6 Spirit</a></span><br />Durability 90 / 90<br />Requires Level 80<br />Item Level 226<br /></td></tr></table><table><tr><td><span class=\"q2\">Equip: Increases spell power by <!--rtg45-->115.</span><br /><span class=\"q2\">Equip: Increases your haste rating by <!--rtg36-->59&nbsp;<small>(<!--rtg%36-->1.80%&nbsp;@&nbsp;L<!--lvl-->80)</small>.</span><br /><div class=\"q1 whtt-sellprice\">Sell Price: <span class=\"moneygold\">10</span> <span class=\"moneysilver\">52</span> <span class=\"moneycopper\">48</span></div></td></tr></table><!--?45482:1:80:80-->","link":"https://wotlkdb.com?item=45482","ilvl":"226","wowClass":"4","wowSubClass":"2","slot":"7"},{"id":"45481","name":"Gauntlets of Ruthless Reprisal","quality":"4","icon":"inv_gauntlets_29","htmlTooltip":"<table><tr><td><b class=\"q4\">Gauntlets of Ruthless Reprisal</b><br /><!--bo-->Binds when picked up<table width=\"100%\"><tr><td>Hands</td><th><!--asc4-->Plate</th></tr></table><span><!--amr-->1467 Armor</span><br /><span><!--stat4-->+98 Strength</span><br /><span><!--stat7-->+96 Stamina</span><br /><!--e--><!--ps-->Durability 55 / 55<br />Requires Level 80<br />Item Level 226<br /></td></tr></table><table><tr><td><span class=\"q2\">Equip: Increases your haste rating by <!--rtg36-->49&nbsp;<small>(<!--rtg%36-->1.49%&nbsp;@&nbsp;L<!--lvl-->80)</small>.</span><br /><span class=\"q2\">Equip: Improves critical strike rating by <!--rtg32-->60&nbsp;<small>(<!--rtg%32-->1.31%&nbsp;@&nbsp;L<!--lvl-->80)</small>.</span><br /><div class=\"q1 whtt-sellprice\">Sell Price: <span class=\"moneygold\">7</span> <span class=\"moneysilver\">38</span> <span class=\"moneycopper\">8</span></div></td></tr></table><!--?45481:1:80:80-->","link":"https://wotlkdb.com?item=45481","ilvl":"226","wowClass":"4","wowSubClass":"4","slot":"10"},{"id":"45487","name":"Handguards of Revitalization","quality":"4","icon":"inv_gauntlets_62","htmlTooltip":"<table><tr><td><b class=\"q4\">Handguards of Revitalization</b><br /><!--bo-->Binds when picked up<table width=\"100%\"><tr><td>Hands</td><th><!--asc4-->Plate</th></tr></table><span><!--amr-->1512 Armor</span><br /><span><!--stat4-->+84 Strength</span><br /><span><!--stat7-->+127 Stamina</span><br /><!--e--><span class=\"socket-red q0\" >Red Socket</span><br /><span class=\"socket-yellow q0\" >Yellow Socket</span><br /><!--ps--><span class=\"q0\">Socket Bonus: <a href=\"?enchantment=3307\">+9 Stamina</a></span><br />Durability 55 / 55<br />Requires Level 80<br />Item Level 239<br /></td></tr></table><table><tr><td><span class=\"q2\">Equip: Increases defense rating by <!--rtg12-->44&nbsp;<small>(<!--rtg%12-->8.95&nbsp;@&nbsp;L<!--lvl-->80)</small>.</span><br /><span class=\"q2\">Equip: Increases your dodge rating by <!--rtg13-->44&nbsp;<small>(<!--rtg%13-->0.97%&nbsp;@&nbsp;L<!--lvl-->80)</small>.</span><br /><span class=\"q2\">Equip: Increases your parry rating by <!--rtg14-->46&nbsp;<small>(<!--rtg%14-->1.02%&nbsp;@&nbsp;L<!--lvl-->80)</small>.</span><br /><div class=\"q1 whtt-sellprice\">Sell Price: <span class=\"moneygold\">8</span> <span class=\"moneysilver\">18</span> <span class=\"moneycopper\">20</span></div></td></tr></table><!--?45487:1:80:80-->","link":"https://wotlkdb.com?item=45487","ilvl":"239","wowClass":"4","wowSubClass":"4","slot":"10"}],"jewelry":[{"id":"45480","name":"Nymph Heart Charm","quality":"4","icon":"inv_jewelry_necklace_10","htmlTooltip":"<table><tr><td><b class=\"q4\">Nymph Heart Charm</b><br /><!--bo-->Binds when equipped<table width=\"100%\"><tr><td>Neck</td></tr></table><span><!--stat3-->+63 Agility</span><br /><span><!--stat7-->+63 Stamina</span><br /><!--e--><!--ps-->Requires Level 80<br />Item Level 226<br /></td></tr></table><table><tr><td><span class=\"q2\">Equip: Increases attack power by <!--rtg38-->92.</span><br /><span class=\"q2\">Equip: Improves hit rating by <!--rtg31-->36&nbsp;<small>(<!--rtg%31-->1.10%&nbsp;@&nbsp;L<!--lvl-->80)</small>.</span><br /><span class=\"q2\">Equip: Increases your haste rating by <!--rtg36-->42&nbsp;<small>(<!--rtg%36-->1.28%&nbsp;@&nbsp;L<!--lvl-->80)</small>.</span><br /><div class=\"q1 whtt-sellprice\">Sell Price: <span class=\"moneygold\">7</span> <span class=\"moneysilver\">56</span> <span class=\"moneycopper\">23</span></div></td></tr></table><!--?45480:1:80:80-->","link":"https://wotlkdb.com?item=45480","ilvl":"226","wowClass":"4","wowSubClass":"-3","slot":"2"},{"id":"45485","name":"Bronze Pendant of the Vanir","quality":"4","icon":"inv_jewelry_necklace_47","htmlTooltip":"<table><tr><td><b class=\"q4\">Bronze Pendant of the Vanir</b><br /><!--bo-->Binds when picked up<table width=\"100%\"><tr><td>Neck</td></tr></table><span><!--stat4-->+71 Strength</span><br /><span><!--stat7-->+96 Stamina</span><br /><!--e--><span class=\"socket-yellow q0\" >Yellow Socket</span><br /><!--ps--><span class=\"q0\">Socket Bonus: <a href=\"?enchantment=2868\">+6 Stamina</a></span><br />Requires Level 80<br />Item Level 239<br /></td></tr></table><table><tr><td><span class=\"q2\">Equip: Increases defense rating by <!--rtg12-->37&nbsp;<small>(<!--rtg%12-->7.52&nbsp;@&nbsp;L<!--lvl-->80)</small>.</span><br /><span class=\"q2\">Equip: Increases your dodge rating by <!--rtg13-->30&nbsp;<small>(<!--rtg%13-->0.66%&nbsp;@&nbsp;L<!--lvl-->80)</small>.</span><br /><span class=\"q2\">Equip: Increases your parry rating by <!--rtg14-->37&nbsp;<small>(<!--rtg%14-->0.82%&nbsp;@&nbsp;L<!--lvl-->80)</small>.</span><br /><div class=\"q1 whtt-sellprice\">Sell Price: <span class=\"moneygold\">7</span> <span class=\"moneysilver\">56</span> <span class=\"moneycopper\">23</span></div></td></tr></table><!--?45485:1:80:80-->","link":"https://wotlkdb.com?item=45485","ilvl":"239","wowClass":"4","wowSubClass":"-3","slot":"2"}],"weapons":[{"id":"46017","name":"Val'anyr, Hammer of Ancient Kings","quality":"5","icon":"inv_mace_99","htmlTooltip":"<table><tr><td><b class=\"q5\">Val'anyr, Hammer of Ancient Kings</b><br /><!--bo-->Binds when picked up<table width=\"100%\"><tr><td>Main Hand</td><th>Mace</th></tr></table><table width=\"100%\"><tr><td><!--dmg-->97 - 310 Damage</td><th>Speed <!--spd-->1.80</th></tr></table><!--dps-->(113.1 damage per second)<br /><span><!--stat7-->+55 Stamina</span><br /><span><!--stat5-->+57 Intellect</span><br /><!--e--><!--ps-->Durability 125 / 125<br />Requires Level 80<br />Item Level 245<br /></td></tr></table><table><tr><td><span class=\"q2\">Equip: Increases spell power by <!--rtg45-->621.</span><br /><span class=\"q2\">Equip: Improves critical strike rating by <!--rtg32-->50&nbsp;<small>(<!--rtg%32-->1.09%&nbsp;@&nbsp;L<!--lvl-->80)</small>.</span><br /><span class=\"q2\">Equip: Increases your haste rating by <!--rtg36-->49&nbsp;<small>(<!--rtg%36-->1.49%&nbsp;@&nbsp;L<!--lvl-->80)</small>.</span><br /><span class=\"q2\">Equip: Your healing spells have a chance to cause Blessing of Ancient Kings for 15 sec allowing your heals to shield the target absorbing damage equal to 15% of the amount healed.</span><br /><span class=\"q\">\"The power of creation courses through this weapon.\"</span><div class=\"q1 whtt-sellprice\">Sell Price: <span class=\"moneygold\">36</span> <span class=\"moneysilver\">36</span> <span class=\"moneycopper\">51</span></div></td></tr></table><!--?46017:1:80:80-->","link":"https://wotlkdb.com?item=46017","ilvl":"245","wowClass":"2","wowSubClass":"4","slot":"21"},{"id":"45479","name":"The Lifebinder","quality":"4","icon":"inv_staff_93","htmlTooltip":"<table><tr><td><b class=\"q4\">The Lifebinder</b><br /><!--bo-->Binds when picked up<table width=\"100%\"><tr><td>Two-Hand</td><th>Staff</th></tr></table><table width=\"100%\"><tr><td><!--dmg-->231 - 427 Damage</td><th>Speed <!--spd-->2.10</th></tr></table><!--dps-->(156.7 damage per second)<br /><span class=\"c11\"><!--fap-->(1426 Feral Attack Power)</span><br /><span><!--stat7-->+120 Stamina</span><br /><span><!--stat5-->+121 Intellect</span><br /><span><!--stat6-->+80 Spirit</span><br /><!--e--><!--ps-->Durability 120 / 120<br />Requires Level 80<br />Item Level 232<br /></td></tr></table><table><tr><td><span class=\"q2\">Equip: Increases spell power by <!--rtg45-->550.</span><br /><span class=\"q2\">Equip: Increases your haste rating by <!--rtg36-->120&nbsp;<small>(<!--rtg%36-->3.66%&nbsp;@&nbsp;L<!--lvl-->80)</small>.</span><br /><div class=\"q1 whtt-sellprice\">Sell Price: <span class=\"moneygold\">29</span> <span class=\"moneysilver\">49</span> <span class=\"moneycopper\">10</span></div></td></tr></table><!--?45479:1:80:80-->","link":"https://wotlkdb.com?item=45479","ilvl":"232","wowClass":"2","wowSubClass":"10","slot":"17"},{"id":"45613","name":"Dreambinder","quality":"4","icon":"inv_staff_93","htmlTooltip":"<table><tr><td><b class=\"q4\">Dreambinder</b><br /><!--bo-->Binds when picked up<table width=\"100%\"><tr><td>Two-Hand</td><th>Staff</th></tr></table><table width=\"100%\"><tr><td><!--dmg-->469 - 705 Damage</td><th>Speed <!--spd-->2.40</th></tr></table><!--dps-->(244.6 damage per second)<br /><span class=\"c11\"><!--fap-->(2657 Feral Attack Power)</span><br /><span><!--stat3-->+112 Agility</span><br /><span><!--stat7-->+105 Stamina</span><br /><!--e--><span class=\"socket-yellow q0\" >Yellow Socket</span><br /><span class=\"socket-blue q0\" >Blue Socket</span><br /><!--ps--><span class=\"q0\">Socket Bonus: <a href=\"?enchantment=3313\">+8 Agility</a></span><br />Durability 120 / 120<br />Requires Level 80<br />Item Level 239<br /></td></tr></table><table><tr><td><span class=\"q2\">Equip: Increases attack power by <!--rtg38-->140.</span><br /><span class=\"q2\">Equip: Increases your haste rating by <!--rtg36-->86&nbsp;<small>(<!--rtg%36-->2.62%&nbsp;@&nbsp;L<!--lvl-->80)</small>.</span><br /><span class=\"q2\">Equip: Increases your armor penetration rating by <!--rtg44-->85&nbsp;<small>(<!--rtg%44-->6.07%&nbsp;@&nbsp;L<!--lvl-->80)</small>.</span><br /><div class=\"q1 whtt-sellprice\">Sell Price: <span class=\"moneygold\">30</span> <span class=\"moneysilver\">44</span> <span class=\"moneycopper\">2</span></div></td></tr></table><!--?45613:1:80:80-->","link":"https://wotlkdb.com?item=45613","ilvl":"239","wowClass":"2","wowSubClass":"10","slot":"17"},{"id":"45484","name":"Bladetwister","quality":"4","icon":"inv_weapon_shortblade_93","htmlTooltip":"<table><tr><td><b class=\"q4\">Bladetwister</b><br /><!--bo-->Binds when picked up<table width=\"100%\"><tr><td>One-Hand</td><th>Dagger</th></tr></table><table width=\"100%\"><tr><td><!--dmg-->184 - 343 Damage</td><th>Speed <!--spd-->1.40</th></tr></table><!--dps-->(188.2 damage per second)<br /><span><!--stat3-->+55 Agility</span><br /><span><!--stat7-->+48 Stamina</span><br /><!--e--><span class=\"socket-blue q0\" >Blue Socket</span><br /><!--ps--><span class=\"q0\">Socket Bonus: <a href=\"?enchantment=2877\">+4 Agility</a></span><br />Durability 75 / 75<br />Requires Level 80<br />Item Level 239<br /></td></tr></table><table><tr><td><span class=\"q2\">Equip: Increases attack power by <!--rtg38-->64.</span><br /><span class=\"q2\">Equip: Increases your haste rating by <!--rtg36-->37&nbsp;<small>(<!--rtg%36-->1.13%&nbsp;@&nbsp;L<!--lvl-->80)</small>.</span><br /><span class=\"q2\">Equip: Improves critical strike rating by <!--rtg32-->28&nbsp;<small>(<!--rtg%32-->0.61%&nbsp;@&nbsp;L<!--lvl-->80)</small>.</span><br /><div class=\"q1 whtt-sellprice\">Sell Price: <span class=\"moneygold\">22</span> <span class=\"moneysilver\">37</span> <span class=\"moneycopper\">35</span></div></td></tr></table><!--?45484:1:80:80-->","link":"https://wotlkdb.com?item=45484","ilvl":"239","wowClass":"2","wowSubClass":"15","slot":"13"}],"tokens":[{"id":"45653","name":"Legplates of the Wayward Conqueror","quality":"4","icon":"inv_pants_plate_17","htmlTooltip":"<table><tr><td><b class=\"q4\">Legplates of the Wayward Conqueror</b><br /><!--bo-->Binds when picked up<br /><!--e--><!--ps-->Classes: <a href=\"?class=2\" class=\"c2\">Paladin</a>, <a href=\"?class=5\" class=\"c5\">Priest</a>, <a href=\"?class=9\" class=\"c9\">Warlock</a><br />Requires Level 80<br /></td></tr></table><table><tr><td><div class=\"q1 whtt-sellprice\">Sell Price: <span class=\"moneygold\">5</span> </div></td></tr></table><!--?45653:1:1:80-->","link":"https://wotlkdb.com?item=45653","ilvl":"80","wowClass":"15","wowSubClass":"-2","slot":"0"},{"id":"45654","name":"Legplates of the Wayward Protector","quality":"4","icon":"inv_pants_plate_17","htmlTooltip":"<table><tr><td><b class=\"q4\">Legplates of the Wayward Protector</b><br /><!--bo-->Binds when picked up<br /><!--e--><!--ps-->Classes: <a href=\"?class=1\" class=\"c1\">Warrior</a>, <a href=\"?class=3\" class=\"c3\">Hunter</a>, <a href=\"?class=7\" class=\"c7\">Shaman</a><br />Requires Level 80<br /></td></tr></table><table><tr><td><div class=\"q1 whtt-sellprice\">Sell Price: <span class=\"moneygold\">5</span> </div></td></tr></table><!--?45654:1:1:80-->","link":"https://wotlkdb.com?item=45654","ilvl":"80","wowClass":"15","wowSubClass":"-2","slot":"0"},{"id":"45655","name":"Legplates of the Wayward Vanquisher","quality":"4","icon":"inv_pants_plate_17","htmlTooltip":"<table><tr><td><b class=\"q4\">Legplates of the Wayward Vanquisher</b><br /><!--bo-->Binds when picked up<br /><!--e--><!--ps-->Classes: <a href=\"?class=4\" class=\"c4\">Rogue</a>, <a href=\"?class=6\" class=\"c6\">Death Knight</a>, <a href=\"?class=8\" class=\"c8\">Mage</a>, <a href=\"?class=11\" class=\"c11\">Druid</a><br />Requires Level 80<br /></td></tr></table><table><tr><td><div class=\"q1 whtt-sellprice\">Sell Price: <span class=\"moneygold\">5</span> </div></td></tr></table><!--?45655:1:1:80-->","link":"https://wotlkdb.com?item=45655","ilvl":"80","wowClass":"15","wowSubClass":"-2","slot":"0"}],"misc":[{"id":"45038","name":"Fragment of Val'anyr","quality":"5","icon":"inv_ingot_titansteel_red","htmlTooltip":"<table><tr><td><b class=\"q5\">Fragment of Val'anyr</b><br /><!--bo-->Binds when picked up<br />Unique (30)<br /><!--e--><!--ps-->Classes: <a href=\"?class=2\" class=\"c2\">Paladin</a>, <a href=\"?class=5\" class=\"c5\">Priest</a>, <a href=\"?class=7\" class=\"c7\">Shaman</a>, <a href=\"?class=11\" class=\"c11\">Druid</a><br />Requires Level 80<br /></td></tr></table><table><tr><td><span class=\"q2\">Use: Combines 30 Fragments of Val'anyr to form the Shattered Fragments of Val'anyr.</span><br /><span class=\"q\">\"The fragments of this ancient hammer glow with a cool, soothing light.\"</span><br /><span class=\"q1\">1 Charge</span></td></tr></table><!--?45038:1:1:80-->","link":"https://wotlkdb.com?item=45038","ilvl":"80","wowClass":"0","wowSubClass":"0","slot":"0"},{"id":"46110","name":"Alchemist's Cache","quality":"3","icon":"inv_misc_bag_18","htmlTooltip":"<table><tr><td><b class=\"q3\">Alchemist's Cache</b><br /><!--bo-->Binds when picked up<br /><!--e--><!--ps-->Requires <a class=\"q1\" href=\"?skill=171\">Alchemy</a> (425)<br /><span class=\"q2\">&lt;Right Click To Open&gt</span><br /></td></tr></table><table><tr><td><div class=\"q1 whtt-sellprice\">Sell Price: <span class=\"moneysilver\">6</span> <span class=\"moneycopper\">25</span></div></td></tr></table><!--?46110:1:1:80-->","link":"https://wotlkdb.com?item=46110","ilvl":"80","wowClass":"15","wowSubClass":"0","slot":"0"},{"id":"45814","name":"Freya's Sigil","quality":"1","icon":"inv_sigil_freya","htmlTooltip":"<table><tr><td><b class=\"q1\">Freya's Sigil</b><br /><!--bo-->Quest Item<br /><!--e--><!--ps--></td></tr></table><table><tr><td></td></tr></table><!--?45814:1:1:80-->","link":"https://wotlkdb.com?item=45814","ilvl":"0","wowClass":"0","wowSubClass":"0","slot":"0"}]},"sortedLootHeroic":{"armor":[],"jewelry":[],"weapons":[],"misc":[],"tokens":[]},"sortedLootHeroicItems":{"armor":[],"jewelry":[],"weapons":[],"tokens":[],"misc":[]}}